stackit/mongodbflex/__init__.py
stackit/mongodbflex/api/__init__.py
stackit/mongodbflex/api/default_api.py
stackit/mongodbflex/api_client.py
stackit/mongodbflex/api_response.py
stackit/mongodbflex/configuration.py
stackit/mongodbflex/exceptions.py
stackit/mongodbflex/models/__init__.py
stackit/mongodbflex/models/acl.py
stackit/mongodbflex/models/backup.py
stackit/mongodbflex/models/backup_schedule.py
stackit/mongodbflex/models/clone_instance_payload.py
stackit/mongodbflex/models/clone_instance_response.py
stackit/mongodbflex/models/create_instance_payload.py
stackit/mongodbflex/models/create_instance_response.py
stackit/mongodbflex/models/create_user_payload.py
stackit/mongodbflex/models/create_user_response.py
stackit/mongodbflex/models/data_point.py
stackit/mongodbflex/models/error.py
stackit/mongodbflex/models/flavor.py
stackit/mongodbflex/models/get_backup_response.py
stackit/mongodbflex/models/get_user_response.py
stackit/mongodbflex/models/handlers_instances_slow_queries_response.py
stackit/mongodbflex/models/handlers_instances_suggested_indexes_response.py
stackit/mongodbflex/models/host.py
stackit/mongodbflex/models/host_metric.py
stackit/mongodbflex/models/instance.py
stackit/mongodbflex/models/instance_flavor.py
stackit/mongodbflex/models/instance_list_instance.py
stackit/mongodbflex/models/instance_response.py
stackit/mongodbflex/models/instance_response_user.py
stackit/mongodbflex/models/list_backups_response.py
stackit/mongodbflex/models/list_flavors_response.py
stackit/mongodbflex/models/list_instances_response.py
stackit/mongodbflex/models/list_metrics_response.py
stackit/mongodbflex/models/list_restore_jobs_response.py
stackit/mongodbflex/models/list_storages_response.py
stackit/mongodbflex/models/list_user.py
stackit/mongodbflex/models/list_users_response.py
stackit/mongodbflex/models/list_versions_response.py
stackit/mongodbflex/models/mongodbatlas_operation.py
stackit/mongodbflex/models/mongodbatlas_stats.py
stackit_mongodbflex-1.2.2.dist-info/METADATA
stackit_mongodbflex-1.2.2.dist-info/WHEEL
stackit_mongodbflex-1.2.2.dist-info/licenses/LICENSE.md
stackit_mongodbflex-1.2.2.dist-info/licenses/NOTICE.txt
stackit_mongodbflex-1.2.2.dist-info/RECORD
